GenCasting/__init__.py
GenCasting/logit_extraction.py
GenCasting-0.0.8.dist-info/LICENSE
GenCasting-0.0.8.dist-info/METADATA
GenCasting-0.0.8.dist-info/WHEEL
GenCasting-0.0.8.dist-info/top_level.txt
GenCasting-0.0.8.dist-info/RECORD
